[
  {
    "name": "Primagama",
    "description": "usaha jasa pendidikan luar sekolah yang bergerak dibidang bimbingan belajar, didirikan tahun 1982",
    "duration": 60,
    "CategoryId": 1
  },
  {
    "name": "ganesa",
    "description": "PT. Pendidikan Ganesha Operation merupakan lembaga bimbingan belajar terbaik dan terbesar di Indonesia. Berdiri sejak 2 Mei 1984 di Kota Bandung",
    "duration": 60,
    "CategoryId": 2
  },
  {
    "name": "Blander",
    "description": "Usaha jasa pendidikan yang sudah berdiri sejak 1900",
    "duration": 120,
    "CategoryId": 3
  }
]
